pyprobar/__init__.py
pyprobar/compose.py
pyprobar/cursor.py
pyprobar/progressbar.py
pyprobar/styleString.py
pyprobar/test_bar.py
pyprobar/test_thread_bar.py
pyprobar/testbar.py
pyprobar/testbar2.py
pyprobar/testterm.py
pyprobar/utils.py
pyprobar/version_config.yaml
pyprobar-0.1.2.0.dist-info/LICENSE
pyprobar-0.1.2.0.dist-info/METADATA
pyprobar-0.1.2.0.dist-info/WHEEL
pyprobar-0.1.2.0.dist-info/top_level.txt
pyprobar-0.1.2.0.dist-info/RECORD
