Metadata-Version: 2.1
Name: pyprobar
Version: 0.1.2.0
Summary: An easy-to-use and colorful progress bar for python.
Home-page: https://github.com/beidongjiedeguang/python-progress-bar
Author: K.y
Author-email: beidongjiedeguang@gmail.com
License: MIT
Keywords: Python Utilities,Machine Learning
Platform: UNKNOWN
Classifier: Operating System :: OS Independent
Classifier: Intended Audience :: Developers
Classifier: Intended Audience :: Science/Research
Classifier: Topic :: Scientific/Engineering :: Artificial Intelligence
Classifier: Programming Language :: Python :: 3
Classifier: Programming Language :: Python :: 3.5
Classifier: Programming Language :: Python :: 3.6
Classifier: Programming Language :: Python :: 3.7
Classifier: Programming Language :: Python :: 3.8
Requires-Dist: numpy
Requires-Dist: pyyaml
Requires-Dist: pendulum
